main.py
setup.py
shadowkw.egg-info/PKG-INFO
shadowkw.egg-info/SOURCES.txt
shadowkw.egg-info/dependency_links.txt
shadowkw.egg-info/requires.txt
shadowkw.egg-info/top_level.txt